{
  "id": "day-353",
  "day": 353,
  "date": "2026-12-19",
  "title": "Better Days",
  "artist": "TH3SCR1B3",
  "bpm": 74,
  "duration": 246,
  "mood": "dark",
  "valence": 0.5700402178667392,
  "moodTags": [
    "reflective",
    "tense",
    "ballad"
  ],
  "description": "Exploring self_discovery and social_commentary.",
  "audioUrl": "https://pznmptudgicrmljjafex.supabase.co/storage/v1/object/public/releaseready/audio/december/19%20-%20Better%20Days.mp3",
  "coverArt": "https://pznmptudgicrmljjafex.supabase.co/storage/v1/object/public/releaseready/covers/december/19%20-%20Better%20Days.jpg",
  "notes": [
    {
      "time": 3.041,
      "lane": 2,
      "type": "tap",
      "id": 0
    },
    {
      "time": 7.905,
      "lane": 0,
      "type": "tap",
      "id": 1
    },
    {
      "time": 9.527,
      "lane": 1,
      "type": "hold",
      "holdDuration": 1.216,
      "id": 2
    },
    {
      "time": 11.959,
      "lane": 2,
      "type": "tap",
      "id": 3
    },
    {
      "time": 13.581,
      "lane": 0,
      "type": "tap",
      "id": 4
    },
    {
      "time": 15.203,
      "lane": 1,
      "type": "tap",
      "id": 5
    },
    {
      "time": 16.824,
      "lane": 2,
      "type": "tap",
      "id": 6
    },
    {
      "time": 18.446,
      "lane": 0,
      "type": "tap",
      "id": 7
    },
    {
      "time": 20.068,
      "lane": 1,
      "type": "hold",
      "holdDuration": 1.216,
      "id": 8
    },
    {
      "time": 22.5,
      "lane": 2,
      "type": "tap",
      "id": 9
    },
    {
      "time": 24.122,
      "lane": 0,
      "type": "tap",
      "id": 10
    },
    {
      "time": 25.743,
      "lane": 1,
      "type": "tap",
      "id": 11
    },
    {
      "time": 28.986,
      "lane": 2,
      "type": "tap",
      "id": 12
    },
    {
      "time": 30.608,
      "lane": 0,
      "type": "tap",
      "id": 13
    },
    {
      "time": 37.095,
      "lane": 1,
      "type": "hold",
      "holdDuration": 1.216,
      "id": 14
    },
    {
      "time": 39.527,
      "lane": 2,
      "type": "tap",
      "id": 15
    },
    {
      "time": 41.149,
      "lane": 0,
      "type": "tap",
      "id": 16
    },
    {
      "time": 44.392,
      "lane": 1,
      "type": "tap",
      "id": 17
    },
    {
      "time": 46.014,
      "lane": 2,
      "type": "tap",
      "id": 18
    },
    {
      "time": 47.635,
      "lane": 0,
      "type": "tap",
      "id": 19
    },
    {
      "time": 52.5,
      "lane": 1,
      "type": "tap",
      "id": 20
    },
    {
      "time": 54.122,
      "lane": 2,
      "type": "tap",
      "id": 21
    },
    {
      "time": 55.743,
      "lane": 0,
      "type": "tap",
      "id": 22
    },
    {
      "time": 57.365,
      "lane": 1,
      "type": "tap",
      "id": 23
    },
    {
      "time": 60.608,
      "lane": 2,
      "type": "tap",
      "id": 24
    },
    {
      "time": 62.23,
      "lane": 0,
      "type": "tap",
      "id": 25
    },
    {
      "time": 63.851,
      "lane": 1,
      "type": "tap",
      "id": 26
    },
    {
      "time": 67.095,
      "lane": 2,
      "type": "tap",
      "id": 27
    },
    {
      "time": 68.716,
      "lane": 0,
      "type": "tap",
      "id": 28
    },
    {
      "time": 73.581,
      "lane": 1,
      "type": "tap",
      "id": 29
    },
    {
      "time": 75.203,
      "lane": 2,
      "type": "tap",
      "id": 30
    },
    {
      "time": 84.932,
      "lane": 0,
      "type": "tap",
      "id": 31
    },
    {
      "time": 88.176,
      "lane": 1,
      "type": "hold",
      "holdDuration": 1.216,
      "id": 32
    },
    {
      "time": 92.23,
      "lane": 2,
      "type": "tap",
      "id": 33
    },
    {
      "time": 93.851,
      "lane": 0,
      "type": "tap",
      "id": 34
    },
    {
      "time": 95.473,
      "lane": 1,
      "type": "tap",
      "id": 35
    },
    {
      "time": 97.095,
      "lane": 2,
      "type": "tap",
      "id": 36
    },
    {
      "time": 98.716,
      "lane": 0,
      "type": "tap",
      "id": 37
    },
    {
      "time": 100.338,
      "lane": 1,
      "type": "hold",
      "holdDuration": 1.216,
      "id": 38
    },
    {
      "time": 102.77,
      "lane": 2,
      "type": "tap",
      "id": 39
    },
    {
      "time": 104.392,
      "lane": 0,
      "type": "tap",
      "id": 40
    },
    {
      "time": 106.014,
      "lane": 1,
      "type": "tap",
      "id": 41
    },
    {
      "time": 107.635,
      "lane": 2,
      "type": "tap",
      "id": 42
    },
    {
      "time": 112.5,
      "lane": 0,
      "type": "tap",
      "id": 43
    },
    {
      "time": 114.122,
      "lane": 1,
      "type": "tap",
      "id": 44
    },
    {
      "time": 118.986,
      "lane": 2,
      "type": "tap",
      "id": 45
    },
    {
      "time": 120.608,
      "lane": 0,
      "type": "tap",
      "id": 46
    },
    {
      "time": 122.23,
      "lane": 1,
      "type": "tap",
      "id": 47
    },
    {
      "time": 128.716,
      "lane": 2,
      "type": "tap",
      "id": 48
    },
    {
      "time": 135.203,
      "lane": 0,
      "type": "tap",
      "id": 49
    },
    {
      "time": 136.824,
      "lane": 1,
      "type": "hold",
      "holdDuration": 1.216,
      "id": 50
    },
    {
      "time": 140.878,
      "lane": 2,
      "type": "tap",
      "id": 51
    },
    {
      "time": 142.5,
      "lane": 0,
      "type": "tap",
      "id": 52
    },
    {
      "time": 144.122,
      "lane": 1,
      "type": "tap",
      "id": 53
    },
    {
      "time": 147.365,
      "lane": 2,
      "type": "tap",
      "id": 54
    },
    {
      "time": 148.986,
      "lane": 0,
      "type": "tap",
      "id": 55
    },
    {
      "time": 152.23,
      "lane": 1,
      "type": "tap",
      "id": 56
    },
    {
      "time": 155.473,
      "lane": 2,
      "type": "tap",
      "id": 57
    },
    {
      "time": 157.095,
      "lane": 0,
      "type": "tap",
      "id": 58
    },
    {
      "time": 161.959,
      "lane": 1,
      "type": "tap",
      "id": 59
    },
    {
      "time": 163.581,
      "lane": 2,
      "type": "tap",
      "id": 60
    },
    {
      "time": 165.203,
      "lane": 0,
      "type": "tap",
      "id": 61
    },
    {
      "time": 166.824,
      "lane": 1,
      "type": "hold",
      "holdDuration": 1.216,
      "id": 62
    },
    {
      "time": 170.878,
      "lane": 2,
      "type": "tap",
      "id": 63
    },
    {
      "time": 172.5,
      "lane": 0,
      "type": "tap",
      "id": 64
    }
  ],
  "key": "C major",
  "genre": [
    "Ballad",
    "Ambient"
  ],
  "difficultyLevel": 3,
  "lyrics": "[Music] Looking for free Just seems to be a better day I'm remembered to hear the things that you told yourself and it not filled with fear and the whole world dies inside with fear in your eyes. Hey [Outro] I can't hear that sound anymore I can't hear the news and all these lies, yeah If there were better ways we could find better days And there are [Outro] lose their light keep searching for the better days the better days keep searching for a better alone if I could be better and tell people not to do the silly dumb things I would but it doesn't matter how Cool. Oh, yeah. Oh, what's up, dude? What's up, man? Yeah, long time no see, no doubt. I'm just coming back like I fell out. All right. But yeah, it's all good. Thanks for like, hopping in, man. Sorry I couldn't help you out, you know what I'm saying? But, uh, yeah, man.",
  "lyricsSegments": [
    {
      "end": 12,
      "text": "[Music]",
      "start": 0
    },
    {
      "end": 23.5,
      "text": "Looking for free Just seems to be a better day",
      "start": 11.5
    },
    {
      "end": 69.5,
      "text": "I'm remembered to hear the things that you told yourself and it not filled with fear and the whole world dies inside with fear in your eyes.",
      "start": 57.5
    },
    {
      "end": 92.5,
      "text": "Hey",
      "start": 80.5
    },
    {
      "end": 115.5,
      "text": "[Outro]",
      "start": 103.5
    },
    {
      "end": 138.5,
      "text": "I can't hear that sound anymore",
      "start": 126.5
    },
    {
      "end": 150,
      "text": "I can't hear the news and all these lies, yeah If there were better ways we could find better days And there are",
      "start": 138
    },
    {
      "end": 161.5,
      "text": "[Outro]",
      "start": 149.5
    },
    {
      "end": 173,
      "text": "lose their light keep searching for the better days the better days keep searching for a better",
      "start": 161
    },
    {
      "end": 196,
      "text": "alone if I could be better and tell people not to do the silly dumb things I would but it doesn't matter how",
      "start": 184
    },
    {
      "end": 230.5,
      "text": "Cool. Oh, yeah. Oh, what's up, dude? What's up, man? Yeah, long time no see, no doubt. I'm just coming back like I fell out. All right.",
      "start": 218.5
    },
    {
      "end": 242,
      "text": "But yeah, it's all good. Thanks for like, hopping in, man. Sorry I couldn't help you out, you know what I'm saying? But, uh, yeah, man.",
      "start": 230
    }
  ],
  "unlock": {
    "card": "card-353",
    "fragments": 10
  }
}