{
  "id": "card-103",
  "day": 103,
  "title": "My Way",
  "storageTitle": "My Way",
  "mood": "dark",
  "rarity": "common",
  "energy": 0.6639630536403749,
  "valence": 0.3980925796198197,
  "tempo": 77,
  "genre": [
    "Ballad",
    "Ambient"
  ],
  "tags": [
    "reflective",
    "conflicted",
    "ballad"
  ],
  "coverUrl": "https://pznmptudgicrmljjafex.supabase.co/storage/v1/object/public/releaseready/covers/april/13%20-%20My%20Way.jpg",
  "audioUrl": "https://pznmptudgicrmljjafex.supabase.co/storage/v1/object/public/releaseready/audio/april/my%20way_relay_m_mastered.mp3",
  "description": "Exploring heartbreak and relationship struggles.",
  "claimedCount": 1,
  "maxSupply": 100,
  "song": "day-103"
}