{
  "id": "card-305",
  "day": 305,
  "title": "Never gonna Stop Loving You",
  "storageTitle": "1 2",
  "mood": "dark",
  "rarity": "uncommon",
  "energy": 0.31775630046496556,
  "valence": 0.4316337796116636,
  "tempo": 110,
  "genre": [
    "Alternative",
    "Indie"
  ],
  "tags": [
    "conflicted",
    "introspective",
    "alternative"
  ],
  "coverUrl": "https://pznmptudgicrmljjafex.supabase.co/storage/v1/object/public/releaseready/covers/november/01%20-%20Never%20gonna%20Stop%20Loving%20You.jpg",
  "audioUrl": "https://pznmptudgicrmljjafex.supabase.co/storage/v1/object/public/releaseready/audio/november/01%20-%201%202.mp3",
  "description": "Exploring identity and relationship complexity.",
  "claimedCount": 36,
  "maxSupply": 100,
  "song": "day-305"
}